{
  "display": {
    "icon": {
      "item": "charmncraft-bits:companion_block_plushieie"
    },
    "title": "99.9% Non-Organic Material!",
    "description": "Obtain a Companion Cube plushie",
    "frame": "task",
    "show_toast": true,
    "announce_to_chat": false,
    "hidden": false
  },
  "criteria": {
    "get_companion_block_plushie": {
      "trigger": "minecraft:inventory_changed",
      "conditions": {
        "items": [
          {
            "items": [
              "charmncraft-bits:companion_block_plushieie"
            ],
            "count": {
              "min": 1,
              "max": 2368
            }
          }
        ]
      }
    }
  },
  "rewards": {
    "experience": 0,
    "function": "charmncraft-bits:first_rare_plushie_trigger"
  },
  "parent": "charmncraft-bits:get_heavy_plushie"
}